ComplexPipeline/complex_pipeline.v
//A complex pipeline function of ALU 
//The intermediate latches required are declared 
//just before they are used, for better code readability. 
module complex_pipeline ( Zout , rs1, rs2, rd, func, addr, clk1, clk2) ; 
	output [15:0] Zout ; 
	input [3:0] rs1, rs2, rd; 
	//rs1 and rs2 are the source registers, and rd is the destination 
	//register. 
	input [3:0] func ; 
	//func is the opcode for the ALU operations 
	input [7:0] addr ; //8 bit address lines for 256 locations of memory 
	input write ; 
	input clk1, clk2 ; //Two phase clock
	
	
	
	reg [15:0] regbank [15:0] ; //Register Bank 
	reg [15:0] mem [255:0] ; //Memory block - 256 x 16 memory 
	
	//Stage 1 - clk1 is connected here 
	reg [15:0] L12_A, L12_B ; 
	reg [3:0] L12_rd ; 
	reg [3:0] L12_func ; 
	reg [7:0] L12_addr ;
	 
	always @ ( posedge clk1 ) 
		begin 
			L12_A <= regbank[rs1] ; 
			L12_B <= regbank[rs2] ; 
			L12_rd <= rd ; 
			L12_func <= func ; 
			L12_addr <= addr ; 
		end 
	
	//Stage 2 - clk 2 is connected here
	reg [15:0] L23_Z  ; 
	reg [3:0] L23_rd ; 
	reg [7:0] L23_addr ; 
	
	always @ ( negedge clk2 ) 
		begin 
			case(L12_func) 
			0: L23_Z <= L12_A + L12_B ; 
			1: L23_Z <= L12_A - L12_B ; 
			2: L23_Z <= L12_A * L12_B ; 
			3: L23_Z <= L12_A ; 
			4: L23_Z <= L12_B ; 
			5: L23_Z <= L12_A & L12_B ; 
			6: L23_Z <= L12_A | L12_B ; 
			7: L23_Z <= L12_A ^ L12_B ; 
			8: L23_Z <= - L12_A ; 
			9: L23_Z <= - L12_B ; 
			10: L23_Z <= L12_A >> 1 ; 
			11: L23_Z <= L12_A << 1 ; 
			default : L23_Z <= 16'hxxxx ; 
			endcase 
		L23_rd <= L12_rd ; 
		L23_addr <= L12_addr ; 
		end 
		
	
	//Stage 3 - clk 1 is connected here 
	reg [15:0] L34_Z ; 
	reg [7:0] L34_addr ; 
	
	always @ ( posedge clk1) 
		begin 
			regbank[L23_rd] <= L23_Z ; 
			L34_Z <= L23_Z ; 
			L34_addr <= L23_addr ; 
		end 
	
	//Stage 4 - clk 2 is used here 
	always @ ( negedge clk2) 
		begin 
			mem[L34_addr] <= L34_Z ; 
		end 
	
	assign Zout = L34_Z ; 
endmodule

ComplexPipeline/complex_pipeline_tb.v
module complex_pipeline_tb ; 

wire [15:0] Z ; 
reg [3:0] rs1, rs2, rd, func ; 
reg [7:0] addr ; 
reg clk1, clk2 ; 
integer k ; 

complex_pipeline DUT (Z, rs1, rs2, rd, func, addr, clk1, clk2 ) ; 

initial 
	begin 
		clk1 = 0 ; 
		clk2 = 0 ; 
		
		repeat(20) //Generating two-phase clock 
			begin 
				#5 clk1 = 1 ; 
				#5 clk1 = 0 ; 
				#5 clk2 = 1 ; 
				#5 clk2 = 0 ; 
			end 
	end 
	
initial 
	for(k = 0 ; k < 16 ; k = k + 1) 
		DUT.regbank[k] = k ;  //Initializine registers 

initial 
	begin 
		#5 rs1 = 3 ; 
		rs2 = 5 ; 
		rd = 10 ; 
		func = 0 ;  //Addition 
		addr = 125 ; 

		#20 rs1 = 3 ; 
		rs2 = 8 ; 
		rd = 12 ; 
		func = 2 ; //Multiplication 
		addr = 126 ; 
		
		#20 rs1 = 10; 
		rs2 = 5 ; 
		rd = 14 ; 
		func = 1 ; //Subtraction 
		addr = 128 ; 
		
		#20 rs1 = 7 ; 
		rs2 = 3 ; 
		rd = 13 ; 
		func = 11 ; 
		addr = 127 ; 
		
		#60 for ( k = 125 ; k < 131 ; k = k + 1 ) 
			begin 
			$display ("Mem[%3d] = %3d", k, DUT.mem[k] ) ; 
			end 
			
	end
	
initial 
	begin 
	$dumpfile("WaveformFile.vcd") ; 
	$dumpvars(0, complex_pipeline_tb) ; 
	$monitor("Time # %d, F = %d", $time, Z ) ; 
	end 
	
endmodule

ComplexPipeline/WaveformFile.vcd
$date
	Wed Sep  2 09:16:41 2020
$end
$version
	Icarus Verilog
$end
$timescale
	1s
$end
$scope module complex_pipeline_tb $end
$var wire 16 ! Z [15:0] $end
$var reg 8 " addr [7:0] $end
$var reg 1 # clk1 $end
$var reg 1 $ clk2 $end
$var reg 4 % func [3:0] $end
$var reg 4 & rd [3:0] $end
$var reg 4 ' rs1 [3:0] $end
$var reg 4 ( rs2 [3:0] $end
$var integer 32 ) k [31:0] $end
$scope module DUT $end
$var wire 16 * Zout [15:0] $end
$var wire 8 + addr [7:0] $end
$var wire 1 # clk1 $end
$var wire 1 $ clk2 $end
$var wire 4 , func [3:0] $end
$var wire 4 - rd [3:0] $end
$var wire 4 . rs1 [3:0] $end
$var wire 4 / rs2 [3:0] $end
$var wire 1 0 write $end
$var reg 16 1 L12_A [15:0] $end
$var reg 16 2 L12_B [15:0] $end
$var reg 8 3 L12_addr [7:0] $end
$var reg 4 4 L12_func [3:0] $end
$var reg 4 5 L12_rd [3:0] $end
$var reg 16 6 L23_Z [15:0] $end
$var reg 8 7 L23_addr [7:0] $end
$var reg 4 8 L23_rd [3:0] $end
$var reg 16 9 L34_Z [15:0] $end
$var reg 8 : L34_addr [7:0] $end
$upscope $end
$upscope $end
$enddefinitions $end
#0
$dumpvars
bx :
bx 9
bx 8
bx 7
bx 6
bx 5
bx 4
bx 3
bx 2
bx 1
z0
bx /
bx .
bx -
bx ,
bx +
bx *
b10000 )
bx (
bx '
bx &
bx %
0$
0#
bx "
bx !
$end
#5
b1111101 3
b0 4
b1010 5
b101 2
b11 1
b1111101 "
b1111101 +
b0 %
b0 ,
b1010 &
b1010 -
b101 (
b101 /
b11 '
b11 .
1#
#10
0#
#15
1$
#20
b1111101 7
b1010 8
b1000 6
0$
#25
b1111101 :
b1000 !
b1000 *
b1000 9
b1111110 3
b10 4
b1100 5
b1000 2
1#
b1111110 "
b1111110 +
b10 %
b10 ,
b1100 &
b1100 -
b1000 (
b1000 /
#30
0#
#35
1$
#40
b1111110 7
b1100 8
b11000 6
0$
#45
b10000000 3
b1 4
b1110 5
b101 2
b1000 1
b1111110 :
b11000 !
b11000 *
b11000 9
1#
b10000000 "
b10000000 +
b1 %
b1 ,
b1110 &
b1110 -
b101 (
b101 /
b1010 '
b1010 .
#50
0#
#55
1$
#60
b10000000 7
b1110 8
b11 6
0$
#65
b10000000 :
b11 !
b11 *
b11 9
b1111111 3
b1011 4
b1101 5
b11 2
b111 1
1#
b1111111 "
b1111111 +
b1011 %
b1011 ,
b1101 &
b1101 -
b11 (
b11 /
b111 '
b111 .
#70
0#
#75
1$
#80
b1111111 7
b1101 8
b1110 6
0$
#85
b1111111 :
b1110 !
b1110 *
b1110 9
1#
#90
0#
#95
1$
#100
0$
#105
1#
#110
0#
#115
1$
#120
0$
#125
1#
b10000011 )
