FSM_Prob/FSM.v
//FSM Prob
//Start time - 11:10 

//Module declaration and defination 
module FSM ( 
	input KEY0, //Clock 
	input SW0, SW1, SW2, SW3, SW4, // Switches to control state transitions 
	output reg [2:0] State, //State of the FSM 
	output reg [1:0] Z  //Z is the output of that particular state of FSM 
		) ; 
		
//State Encoding 
localparam State_0 = 3'd0 , 
			State_1 = 3'd1 , 
			State_2 = 3'd2 , 
			State_3 = 3'd3 , 
			State_4 = 3'd4 ; 
			

//State registers 
//reg [2:0] PS ; //Contains present state 
reg [2:0] NS ; //Contains next state 

//State Transtition Block 
always @ (posedge KEY0) 
	begin 
		if (SW0) 
			State <= State_0 ; 
		else 
			State <= NS ; 
	end 
	

//State Relation Block 
always @ (*) 
	begin 
		NS = State ; 
		
			case(State)
			State_0: begin 
						if(SW2) 
							NS = State_1 ; 
						else if(SW1) 
							NS = State_3; 
						else 
							NS = State ; 
					end 
			
			State_1: begin 
						if(SW1) 
							NS = State_2 ; 
						else 
							NS = State ; 
					end 
			
			State_2: begin 
						if(SW1) 
							NS = State_1 ; 
						else if(SW4) 
							NS = State_3 ; 
						else 
							NS = State ; 
					 end 
			State_3 : begin 
						if(SW1) 
							NS = State_1 ; 
						else if(SW3) 
							NS = State_4 ; 
						else 
							NS = State ; 
					 end 
			State_4:  begin 
						if(SW0) 
							NS = State_0 ; 
						else if(SW1) 
							NS = State_1 ; 
						else 
							NS = State ; 
					end 
			default: begin 
						NS = State ; 
					 end 
		
			endcase 
	
	end 
	
//Outputs -- 2 bit 'Z' 
always @ (*) 
begin 
	case(State) 
	3'd0 : Z = 2'b01 ; 
	3'd1 : Z = 2'b10 ; 
	3'd2 : Z = 2'b00 ; 
	3'd3 : Z = 2'b00 ; 
	3'd4 : Z = 2'b11 ; 
	default: Z = 2'b00 ; //Default Value 
	endcase 
end  

endmodule

FSM_Prob/FSM_tb.v
module FSM_tb ; 


	reg KEY0 = 0;  //Clock 
	reg SW0, SW1, SW2, SW3, SW4 ;  // Switches to control state transitions 
	wire [2:0] State ; //State of the FSM 
	wire [1:0] Z ;  //Z is the output of that particular state of FSM 
	
FSM DUT ( KEY0, SW0, SW1, SW2, SW3, SW4, State, Z ) ; 

		
always 
	begin 
		#5 KEY0 = ~ KEY0 ; 
	 end 
	 

initial 
	#100 $finish ; 
	

initial 
	begin 
		#15 
		  SW0 = 1 ;  
		#10 
		   SW0 = 0 ; 
			SW2 = 1 ; 
		#10 
			SW2 = 0 ; 
			SW1 = 1 ; 
		#10 
		   SW1 = 1 ; 
		#10 
		   SW1 = 1 ; 
		#10 
			SW1 = 0 ; 
			SW4 = 1 ; 
		#10 
			SW4 = 0 ; 
		    SW3 = 1 ; 
		#10 
			SW3 = 0 ; 
		    SW1 = 1 ; 
		    
	end 
	
initial 
	begin 
		$dumpfile ("FSM_Dump.vcd") ; 
		$dumpvars (0, FSM_tb) ; 
		$monitor ("Time = %d, State = %3d ", $time, State) ; 
	end 
	
endmodule

FSM_Prob/FSM_Dump.vcd
$date
	Wed Oct 28 09:38:22 2020
$end
$version
	Icarus Verilog
$end
$timescale
	1s
$end
$scope module FSM_tb $end
$var wire 2 ! Z [1:0] $end
$var wire 3 " State [2:0] $end
$var reg 1 # KEY0 $end
$var reg 1 $ SW0 $end
$var reg 1 % SW1 $end
$var reg 1 & SW2 $end
$var reg 1 ' SW3 $end
$var reg 1 ( SW4 $end
$scope module DUT $end
$var wire 1 # KEY0 $end
$var wire 1 $ SW0 $end
$var wire 1 % SW1 $end
$var wire 1 & SW2 $end
$var wire 1 ' SW3 $end
$var wire 1 ( SW4 $end
$var reg 3 ) NS [2:0] $end
$var reg 3 * State [2:0] $end
$var reg 2 + Z [1:0] $end
$upscope $end
$upscope $end
$enddefinitions $end
#0
$dumpvars
bx +
bx *
bx )
x(
x'
x&
x%
x$
0#
bx "
bx !
$end
#5
1#
#10
0#
#15
b1 !
b1 +
b0 )
b0 "
b0 *
1#
1$
#20
0#
#25
b10 !
b10 +
b1 "
b1 *
b1 )
1#
1&
0$
#30
0#
#35
b0 !
b0 +
b10 "
b10 *
b1 )
1#
1%
0&
#40
0#
#45
b10 !
b10 +
b10 )
b1 "
b1 *
1#
#50
0#
#55
b0 !
b0 +
b1 )
b10 "
b10 *
1#
#60
0#
#65
b11 "
b11 *
b11 )
1#
1(
0%
#70
0#
#75
b11 !
b11 +
b100 "
b100 *
b100 )
1#
1'
0(
#80
0#
#85
b10 !
b10 +
b1 "
b1 *
b10 )
1#
1%
0'
#90
0#
#95
b0 !
b0 +
b1 )
b10 "
b10 *
1#
#100
0#
