Pipelining/pipeline.v
//Pipeline experimentation 
//Implementing a simple function 

//Step 1 : x1 = A + B , x2 = C - D 
//Step 2 : x3 = x1 + x2 
//Step 3 : F = x3*D 

module pipeline ( F, A, B, C, D, clk ) ; 

parameter N = 10 ; //Keep this habbit of always using parameters 

output [N-1:0] F ; 
input [N-1:0] A, B, C, D ; 
input clk ; 

//Stage 1 
reg [N-1:0] L12_x1, L12_x2, L12_D ; 

always @ (posedge clk ) 
	begin 
		L12_x1 <= A + B ; 
		L12_x2 <= C - D ; 
		L12_D <= D ; 
	end 
	
//Stage 2
reg [N-1:0] L23_x3 , L23_D ; 

always @ ( posedge clk ) 
	begin 
		L23_x3 <= L12_x1 + L12_x2 ; 
		L23_D <=  L12_D ; 
	end 
	
//Stage 3 
reg [N-1:0] F_Out ; 
always @ ( posedge clk ) 
	F_Out <= L23_x3 * L23_D ; 
	
assign F = F_Out ; 

endmodule

Pipelining/pipeline_tb.v
module pipeline_tb ; 
parameter N = 10 ; 
wire [N-1:0] F ; //Main module ka output hamesha wire 
reg [N-1:0] A, B, C, D ; //Main module ke inputs hamesha reg
reg clk ; 


//F = ( A + B + C - D ) * D 
pipeline MyPipeDUT ( F, A, B, C, D, clk ) ; 

initial 
	clk = 0 ; 	

always 
	#10 clk = ~clk ; 
	
initial 
	#200 $finish ; 
	
initial 
	begin 
		#10
			A = 0 ; 
			B = 0 ; 
			C = 0 ; 
			D = 0 ; //F = 0
		
		#20
			A = 1 ; 
			B = 2 ; 
			C = 3 ; 
			D = 4 ; // F = 8 
		#20 
			A = 0 ; 
			B = 3 ; 
			C = 5 ; 
			D = 2 ; // F = 12
		#20 
			A = 1 ; 
			B = 0 ; 
			C = 1 ; 
			D = 1 ; // F = 1 
        #20 
			A = 2 ; 
			B = 2 ; 
			C = 2 ; 
			D = 2 ; // F = 8 
		
		
			
	end 

initial 
	begin 
		$dumpfile("pipe1.vcd") ; 
		$dumpvars(0, pipeline_tb ) ; //Dumping all the variables of pipeline_tb 
		$monitor("Time #  %d , F = %d ", $time, F ) ; 
	end 
	

endmodule

Pipelining/pipe1.vcd
$date
	Tue Sep  1 07:52:50 2020
$end
$version
	Icarus Verilog
$end
$timescale
	1s
$end
$scope module pipeline_tb $end
$var wire 10 ! F [9:0] $end
$var reg 10 " A [9:0] $end
$var reg 10 # B [9:0] $end
$var reg 10 $ C [9:0] $end
$var reg 10 % D [9:0] $end
$var reg 1 & clk $end
$scope module MyPipeDUT $end
$var wire 10 ' A [9:0] $end
$var wire 10 ( B [9:0] $end
$var wire 10 ) C [9:0] $end
$var wire 10 * D [9:0] $end
$var wire 10 + F [9:0] $end
$var wire 1 & clk $end
$var reg 10 , F_Out [9:0] $end
$var reg 10 - L12_D [9:0] $end
$var reg 10 . L12_x1 [9:0] $end
$var reg 10 / L12_x2 [9:0] $end
$var reg 10 0 L23_D [9:0] $end
$var reg 10 1 L23_x3 [9:0] $end
$upscope $end
$upscope $end
$enddefinitions $end
#0
$dumpvars
bx 1
bx 0
bx /
bx .
bx -
bx ,
bx +
bx *
bx )
bx (
bx '
0&
bx %
bx $
bx #
bx "
bx !
$end
#10
b0 -
b0 /
b0 .
b0 %
b0 *
b0 $
b0 )
b0 #
b0 (
b0 "
b0 '
1&
#20
0&
#30
b0 0
b0 1
b100 -
b1111111111 /
b11 .
1&
b100 %
b100 *
b11 $
b11 )
b10 #
b10 (
b1 "
b1 '
#40
0&
#50
b10 -
b11 /
b100 0
b10 1
b0 !
b0 +
b0 ,
1&
b10 %
b10 *
b101 $
b101 )
b11 #
b11 (
b0 "
b0 '
#60
0&
#70
b1000 !
b1000 +
b1000 ,
b10 0
b110 1
b1 -
b0 /
b1 .
1&
b1 %
b1 *
b1 $
b1 )
b0 #
b0 (
b1 "
b1 '
#80
0&
#90
b10 -
b100 .
b1 0
b1 1
b1100 !
b1100 +
b1100 ,
1&
b10 %
b10 *
b10 $
b10 )
b10 #
b10 (
b10 "
b10 '
#100
0&
#110
b1 !
b1 +
b1 ,
b10 0
b100 1
1&
#120
0&
#130
b1000 !
b1000 +
b1000 ,
1&
