Clocks/DivideBy2ToThePowerN/DivideBy2.v
//Divide by 2^N 
module DivideBy2 ( 
	input clk_in, 
 
	output clk_out) ; 

integer c = 31 ; //c = 2^N - 1
	
//Assuming the native clock frequency is 50 MHz 

parameter N = 5 ; //Divide the Frequency by 10; 



reg [N-1:0] counter = 0 ; 

always @ ( posedge clk_in ) 
	begin 
			if(counter <= c ) 
					counter = counter + 1 ; 
			else 
				counter = 0 ;
		
	end 

assign clk_out = counter[N-1] ; 

endmodule

Clocks/DivideBy2ToThePowerN/tb_DivideBy2.v
module tb_DivideBy2 ; 

reg clk_in = 0 ; 
wire clk_out ; 

DivideBy2 dut (clk_in, clk_out) ; 


always 
	begin 
		#10 clk_in = ~clk_in ; 
	end 

initial
begin 
	
	$dumpfile("By2.vcd") ; 
	$dumpvars(0, tb_DivideBy2) ;
	#2000 $finish ;  
end 

endmodule

Clocks/DivideBy2ToThePowerN/By2.vcd
$date
	Fri Dec 18 19:32:27 2020
$end
$version
	Icarus Verilog
$end
$timescale
	1s
$end
$scope module tb_DivideBy2 $end
$var wire 1 ! clk_out $end
$var reg 1 " clk_in $end
$scope module dut $end
$var wire 1 " clk_in $end
$var wire 1 ! clk_out $end
$var reg 5 # counter [4:0] $end
$var integer 32 $ c [31:0] $end
$upscope $end
$upscope $end
$enddefinitions $end
#0
$dumpvars
b11111 $
b0 #
0"
0!
$end
#10
b1 #
1"
#20
0"
#30
b10 #
1"
#40
0"
#50
b11 #
1"
#60
0"
#70
b100 #
1"
#80
0"
#90
b101 #
1"
#100
0"
#110
b110 #
1"
#120
0"
#130
b111 #
1"
#140
0"
#150
b1000 #
1"
#160
0"
#170
b1001 #
1"
#180
0"
#190
b1010 #
1"
#200
0"
#210
b1011 #
1"
#220
0"
#230
b1100 #
1"
#240
0"
#250
b1101 #
1"
#260
0"
#270
b1110 #
1"
#280
0"
#290
b1111 #
1"
#300
0"
#310
1!
b10000 #
1"
#320
0"
#330
b10001 #
1"
#340
0"
#350
b10010 #
1"
#360
0"
#370
b10011 #
1"
#380
0"
#390
b10100 #
1"
#400
0"
#410
b10101 #
1"
#420
0"
#430
b10110 #
1"
#440
0"
#450
b10111 #
1"
#460
0"
#470
b11000 #
1"
#480
0"
#490
b11001 #
1"
#500
0"
#510
b11010 #
1"
#520
0"
#530
b11011 #
1"
#540
0"
#550
b11100 #
1"
#560
0"
#570
b11101 #
1"
#580
0"
#590
b11110 #
1"
#600
0"
#610
b11111 #
1"
#620
0"
#630
0!
b0 #
1"
#640
0"
#650
b1 #
1"
#660
0"
#670
b10 #
1"
#680
0"
#690
b11 #
1"
#700
0"
#710
b100 #
1"
#720
0"
#730
b101 #
1"
#740
0"
#750
b110 #
1"
#760
0"
#770
b111 #
1"
#780
0"
#790
b1000 #
1"
#800
0"
#810
b1001 #
1"
#820
0"
#830
b1010 #
1"
#840
0"
#850
b1011 #
1"
#860
0"
#870
b1100 #
1"
#880
0"
#890
b1101 #
1"
#900
0"
#910
b1110 #
1"
#920
0"
#930
b1111 #
1"
#940
0"
#950
1!
b10000 #
1"
#960
0"
#970
b10001 #
1"
#980
0"
#990
b10010 #
1"
#1000
0"
#1010
b10011 #
1"
#1020
0"
#1030
b10100 #
1"
#1040
0"
#1050
b10101 #
1"
#1060
0"
#1070
b10110 #
1"
#1080
0"
#1090
b10111 #
1"
#1100
0"
#1110
b11000 #
1"
#1120
0"
#1130
b11001 #
1"
#1140
0"
#1150
b11010 #
1"
#1160
0"
#1170
b11011 #
1"
#1180
0"
#1190
b11100 #
1"
#1200
0"
#1210
b11101 #
1"
#1220
0"
#1230
b11110 #
1"
#1240
0"
#1250
b11111 #
1"
#1260
0"
#1270
0!
b0 #
1"
#1280
0"
#1290
b1 #
1"
#1300
0"
#1310
b10 #
1"
#1320
0"
#1330
b11 #
1"
#1340
0"
#1350
b100 #
1"
#1360
0"
#1370
b101 #
1"
#1380
0"
#1390
b110 #
1"
#1400
0"
#1410
b111 #
1"
#1420
0"
#1430
b1000 #
1"
#1440
0"
#1450
b1001 #
1"
#1460
0"
#1470
b1010 #
1"
#1480
0"
#1490
b1011 #
1"
#1500
0"
#1510
b1100 #
1"
#1520
0"
#1530
b1101 #
1"
#1540
0"
#1550
b1110 #
1"
#1560
0"
#1570
b1111 #
1"
#1580
0"
#1590
1!
b10000 #
1"
#1600
0"
#1610
b10001 #
1"
#1620
0"
#1630
b10010 #
1"
#1640
0"
#1650
b10011 #
1"
#1660
0"
#1670
b10100 #
1"
#1680
0"
#1690
b10101 #
1"
#1700
0"
#1710
b10110 #
1"
#1720
0"
#1730
b10111 #
1"
#1740
0"
#1750
b11000 #
1"
#1760
0"
#1770
b11001 #
1"
#1780
0"
#1790
b11010 #
1"
#1800
0"
#1810
b11011 #
1"
#1820
0"
#1830
b11100 #
1"
#1840
0"
#1850
b11101 #
1"
#1860
0"
#1870
b11110 #
1"
#1880
0"
#1890
b11111 #
1"
#1900
0"
#1910
0!
b0 #
1"
#1920
0"
#1930
b1 #
1"
#1940
0"
#1950
b10 #
1"
#1960
0"
#1970
b11 #
1"
#1980
0"
#1990
b100 #
1"
